cmem_plugin_graphql/__init__.py
cmem_plugin_graphql/workflow/__init__.py
cmem_plugin_graphql/workflow/graphql.py
cmem_plugin_graphql/workflow/utils.py
cmem_plugin_graphql-5.0.0.dist-info/METADATA
cmem_plugin_graphql-5.0.0.dist-info/WHEEL
cmem_plugin_graphql-5.0.0.dist-info/licenses/LICENSE
cmem_plugin_graphql-5.0.0.dist-info/RECORD
