Metadata-Version: 2.4
Name: cmem-plugin-graphql
Version: 5.0.0
Summary: Send queries to a GraphQL endpoint and save the results in a JSON dataset.
License: Apache-2.0
License-File: LICENSE
Keywords: eccenca Corporate Memory,plugin,GraphQL
Author: eccenca GmbH
Author-email: cmempy-developer@eccenca.com
Requires-Python: >=3.13,<4.0
Classifier: Development Status :: 5 - Production/Stable
Classifier: Environment :: Plugins
Classifier: Intended Audience :: Information Technology
Classifier: License :: OSI Approved :: Apache Software License
Classifier: Programming Language :: Python :: 3
Classifier: Programming Language :: Python :: 3.13
Classifier: Programming Language :: Python :: 3.14
Classifier: Topic :: Software Development :: Libraries :: Python Modules
Requires-Dist: Jinja2 (>=3.1.6,<4.0.0)
Requires-Dist: cmem-plugin-base (>=4.15.0,<5.0.0)
Requires-Dist: gql[all] (>=3.5.3,<4.0.0)
Requires-Dist: graphql-core (>=3.2.6,<4.0.0)
Requires-Dist: validators (>=0.35.0,<0.36.0)
Project-URL: Homepage, https://github.com/eccenca/cmem-plugin-graphql
